docker_secrets/__init__.py
docker_secrets/main.py
docker_secrets_dotenv-0.1.3.dist-info/LICENSE
docker_secrets_dotenv-0.1.3.dist-info/METADATA
docker_secrets_dotenv-0.1.3.dist-info/WHEEL
docker_secrets_dotenv-0.1.3.dist-info/RECORD
