Metadata-Version: 2.3
Name: docker-secrets-dotenv
Version: 0.1.3
Summary: Load docker secrets into ENV
License: MIT
Author: Richard Soper
Requires-Python: >=3.9,<4.0
Classifier: License :: OSI Approved :: MIT License
Classifier: Programming Language :: Python :: 3
Classifier: Programming Language :: Python :: 3.9
Classifier: Programming Language :: Python :: 3.10
Classifier: Programming Language :: Python :: 3.11
Classifier: Programming Language :: Python :: 3.12
Classifier: Programming Language :: Python :: 3.13
Project-URL: Repository, https://gitlab.richardsoper.me/richardsoper/docker-secrets
